searchads_api/__init__.py
searchads_api/api.py
searchads_api-1.7.14.dist-info/LICENSE
searchads_api-1.7.14.dist-info/METADATA
searchads_api-1.7.14.dist-info/WHEEL
searchads_api-1.7.14.dist-info/top_level.txt
searchads_api-1.7.14.dist-info/RECORD
