Metadata-Version: 2.1
Name: searchads_api
Version: 1.7.14
Summary: Apple Searchads API non-official python library
Home-page: https://github.com/phiture/searchads_api
Author: Abdul Majeed Alkattan
Author-email: alkattan@phiture.com
Keywords: python,searchads,library,apple
License-File: LICENSE
Requires-Dist: requests
Requires-Dist: pyjwt
Requires-Dist: cryptography
